src/AnyUserclient/__init__.py
src/AnyUserclient/pyany.py
pyany-0.0.2.dist-info/METADATA
pyany-0.0.2.dist-info/WHEEL
pyany-0.0.2.dist-info/licenses/LICENSE
pyany-0.0.2.dist-info/RECORD
