Metadata-Version: 2.1
Name: pyany
Version: 0.0.2
Summary: Библиотека для помощи в создании User-Client`ов \ Developer: Click ```Creator```
Project-URL: Creator, https://t.me/sasibacka
Project-URL: Mini-Builder, https://t.me/dedinside0011
Project-URL: Host (BETA) for you project, https://t.me/sasibackahost
Author-email: "Сергей - t.me/dedinside0011" <sergeycikkatkovcik@gmail.com>
License-File: LICENSE
Classifier: License :: OSI Approved :: MIT License
Classifier: Operating System :: OS Independent
Classifier: Programming Language :: Python
Requires-Python: >=3.7
